sway_dynamic_names/__init__.py
sway_dynamic_names/__main__.py
sway_dynamic_names/config.py
sway_dynamic_names/daemon.py
sway_dynamic_names/default.yaml
sway_dynamic_names-1.2.1.dist-info/LICENSE
sway_dynamic_names-1.2.1.dist-info/METADATA
sway_dynamic_names-1.2.1.dist-info/WHEEL
sway_dynamic_names-1.2.1.dist-info/entry_points.txt
sway_dynamic_names-1.2.1.dist-info/top_level.txt
sway_dynamic_names-1.2.1.dist-info/RECORD
