Metadata-Version: 2.1
Name: sway-dynamic-names
Version: 1.2.1
Summary: Dynamically update the name of each Sway WM workspace using font-awesome icons
Home-page: https://github.com/j-waters/sway-dynamic-workspace-names
Author: James Waters
Author-email: james@jcwaters.co.uk
License: MIT
Platform: UNKNOWN
Requires-Python: >=3.8
License-File: LICENSE
Requires-Dist: i3ipc
Requires-Dist: pyyaml
Requires-Dist: fontawesome
Requires-Dist: pyxdg
Requires-Dist: Click
